wt/__init__.py
wt/__main__.py
wt/cli.py
wt/launchers.py
wt/worktree.py
git_worktree_cli-0.3.0.dist-info/METADATA
git_worktree_cli-0.3.0.dist-info/WHEEL
git_worktree_cli-0.3.0.dist-info/entry_points.txt
git_worktree_cli-0.3.0.dist-info/licenses/LICENSE
git_worktree_cli-0.3.0.dist-info/RECORD
