Metadata-Version: 2.4
Name: git-worktree-cli
Version: 0.3.0
Summary: A lightweight Python CLI tool to simplify Git worktree management
Project-URL: Homepage, https://github.com/cebidhem/git-worktree-cli
Project-URL: Repository, https://github.com/cebidhem/git-worktree-cli
Project-URL: Issues, https://github.com/cebidhem/git-worktree-cli/issues
Author: cebidhem
License: MIT
License-File: LICENSE
Keywords: claude,cli,developer-tools,git
Classifier: Development Status :: 4 - Beta
Classifier: License :: OSI Approved :: MIT License
Classifier: Programming Language :: Python :: 3.12
Classifier: Programming Language :: Python :: 3.13
Requires-Python: >=3.12
Requires-Dist: typer>=0.9.0
Provides-Extra: dev
Requires-Dist: black>=24.0.0; extra == 'dev'
Requires-Dist: pylint>=3.0.0; extra == 'dev'
Requires-Dist: pytest-mock>=3.0.0; extra == 'dev'
Requires-Dist: pytest>=7.0.0; extra == 'dev'
